ttmask/__init__.py
ttmask/_cli.py
ttmask/add_padding.py
ttmask/box_setup.py
ttmask/cone.py
ttmask/cube.py
ttmask/cuboid.py
ttmask/curved_surface.py
ttmask/cylinder.py
ttmask/ellipsoid.py
ttmask/map2mask.py
ttmask/py.typed
ttmask/soft_edge.py
ttmask/sphere.py
ttmask/tube.py
ttmask-0.1.7.dist-info/METADATA
ttmask-0.1.7.dist-info/WHEEL
ttmask-0.1.7.dist-info/entry_points.txt
ttmask-0.1.7.dist-info/licenses/LICENSE
ttmask-0.1.7.dist-info/RECORD
