Metadata-Version: 2.4
Name: ttmask
Version: 0.1.7
Summary: CLI tool for mask creation in cryo-EM/ET
Project-URL: homepage, https://github.com/teamtomo/ttmask
Project-URL: repository, https://github.com/teamtomo/ttmask
Author-email: Miles Graham <miles.graham@balliol.ox.ac.uk>
License: BSD-3-Clause
License-File: LICENSE
Classifier: Development Status :: 3 - Alpha
Classifier: License :: OSI Approved :: BSD License
Classifier: Programming Language :: Python :: 3
Classifier: Programming Language :: Python :: 3.9
Classifier: Programming Language :: Python :: 3.10
Classifier: Programming Language :: Python :: 3.11
Classifier: Programming Language :: Python :: 3.12
Classifier: Typing :: Typed
Requires-Python: >=3.9
Requires-Dist: einops
Requires-Dist: mrcfile
Requires-Dist: numpy
Requires-Dist: scipy
Requires-Dist: typer
Provides-Extra: dev
Requires-Dist: ipython; extra == 'dev'
Requires-Dist: mkdocs-material; extra == 'dev'
Requires-Dist: mkdocs-video; extra == 'dev'
Requires-Dist: mypy; extra == 'dev'
Requires-Dist: pdbpp; extra == 'dev'
Requires-Dist: pre-commit; extra == 'dev'
Requires-Dist: rich; extra == 'dev'
Requires-Dist: ruff; extra == 'dev'
Provides-Extra: test
Requires-Dist: pytest; extra == 'test'
Requires-Dist: pytest-cov; extra == 'test'
